volleymeet/__init__.py
volleymeet/cli.py
volleymeet/db.py
volleymeet-0.2.0.dist-info/LICENSE
volleymeet-0.2.0.dist-info/METADATA
volleymeet-0.2.0.dist-info/WHEEL
volleymeet-0.2.0.dist-info/entry_points.txt
volleymeet-0.2.0.dist-info/RECORD
