Metadata-Version: 2.1
Name: volleymeet
Version: 0.2.0
Summary: A meeting scheduler developed by Team Volleyball
Home-page: https://github.com/Jython1415/cli-monolithic-architecture
License: MIT
Author: Joshua Shew
Author-email: joshua.t.shew@gmail.com
Requires-Python: >=3.12,<4.0
Classifier: License :: OSI Approved :: MIT License
Classifier: Programming Language :: Python :: 3
Classifier: Programming Language :: Python :: 3.12
